setup.py
weppy_FBAuth.egg-info/PKG-INFO
weppy_FBAuth.egg-info/SOURCES.txt
weppy_FBAuth.egg-info/dependency_links.txt
weppy_FBAuth.egg-info/not-zip-safe
weppy_FBAuth.egg-info/requires.txt
weppy_FBAuth.egg-info/top_level.txt
weppy_fbauth/__init__.py
weppy_fbauth/ext.py