Metadata-Version: 1.1
Name: weppy-FBAuth
Version: 0.1
Summary: Oauth2 login interface for weppy
Home-page: https://github.com/gi0baro/weppy-fbauth
Author: Giovanni Barillari
Author-email: gi0baro@d4net.org
License: BSD
Platform: any
Classifier: Development Status :: 3 - Alpha
Classifier: Environment :: Web Environment
Classifier: Intended Audience :: Developers
Classifier: License :: OSI Approved :: BSD License
Classifier: Operating System :: OS Independent
Classifier: Programming Language :: Python
Classifier: Programming Language :: Python :: 2
Classifier: Programming Language :: Python :: 3
Classifier: Topic :: Internet :: WWW/HTTP :: Dynamic Content
Classifier: Topic :: Software Development :: Libraries :: Python Modules
